itertools_recipes.py
setup.py
itertools_recipes.egg-info/PKG-INFO
itertools_recipes.egg-info/SOURCES.txt
itertools_recipes.egg-info/dependency_links.txt
itertools_recipes.egg-info/top_level.txt