Metadata-Version: 1.0
Name: itertools-recipes
Version: 0.1
Summary: Pasted from the "Recipes" section of the "itertools" documentations: An extended toolset using the existing itertools as building blocks.
Home-page: UNKNOWN
Author: Eddy Mulyono
Author-email: eddymul@gmail.com
License: PSF
Platform: UNKNOWN
